scu_captcha/__init__.py
scu_captcha/configs.py
scu_captcha/model.pt
scu_captcha/model.py
scu_captcha/preData.pt
scu_captcha/scu_captcha.py
scu_captcha-0.0.5.data/data/model.pt
scu_captcha-0.0.5.data/data/preData.pt
scu_captcha-0.0.5.dist-info/LICENSE
scu_captcha-0.0.5.dist-info/METADATA
scu_captcha-0.0.5.dist-info/WHEEL
scu_captcha-0.0.5.dist-info/top_level.txt
scu_captcha-0.0.5.dist-info/RECORD
