Metadata-Version: 2.1
Name: scu-captcha
Version: 0.0.5
Summary: SCU captcha recongnition based on Pytorch
Home-page: https://github.com/SunnyHaze/SCU-Captcha
Author: Sunnyhaze
Author-email: mxch1122@126.com
License: MIT Licence
Project-URL: Authors's Github, https://github.com/SunnyHaze
Project-URL: Repo, https://github.com/SunnyHaze/SCU-Captcha
Keywords: pip,scu-captcha
Platform: UNKNOWN
Classifier: Programming Language :: Python :: 3
Classifier: License :: OSI Approved :: MIT License
Classifier: Operating System :: OS Independent
Requires-Python: >=3.7
License-File: LICENSE
Requires-Dist: requests
Requires-Dist: pillow
